bersona/__init__.py
bersona/_version.py
bersona/astrology_kernel.py
bersona/constants.py
bersona/models.py
bersona/prompts.py
bersona/utils.py
bersona-0.1.3.dist-info/licenses/LICENSE
bersona-0.1.3.dist-info/METADATA
bersona-0.1.3.dist-info/WHEEL
bersona-0.1.3.dist-info/top_level.txt
bersona-0.1.3.dist-info/RECORD
