Metadata-Version: 2.4
Name: bersona
Version: 0.1.3
Summary: Bersona: Astrology chart generation and LLM-based interpretation
Author: fanrenaz
License: MIT
Project-URL: Homepage, https://github.com/fanrenaz/Bersona
Project-URL: Source, https://github.com/fanrenaz/Bersona
Project-URL: Issues, https://github.com/fanrenaz/Bersona/issues
Keywords: astrology,astronomy,llm,chart,skyfield
Classifier: Programming Language :: Python :: 3
Classifier: License :: OSI Approved :: MIT License
Classifier: Intended Audience :: Science/Research
Classifier: Topic :: Scientific/Engineering :: Astronomy
Classifier: Topic :: Scientific/Engineering :: Artificial Intelligence
Requires-Python: >=3.10
License-File: LICENSE
Requires-Dist: skyfield>=1.46
Requires-Dist: pydantic>=2.0
Provides-Extra: placidus
Requires-Dist: pyswisseph>=2.10.3; extra == "placidus"
Provides-Extra: llm
Requires-Dist: openai>=1.0.0; extra == "llm"
Provides-Extra: geocode
Requires-Dist: geopy>=2.4.0; extra == "geocode"
Provides-Extra: all
Requires-Dist: pyswisseph>=2.10.3; extra == "all"
Requires-Dist: openai>=1.0.0; extra == "all"
Requires-Dist: geopy>=2.4.0; extra == "all"
Provides-Extra: dev
Requires-Dist: pytest>=7.0; extra == "dev"
Dynamic: license-file
